[
  {
    "pushed_at": "2021-10-07T16:37:26Z",
    "name": "parallax-bg.el",
    "description": "Parallax backgrounds",
    "open_issues": 0,
    "stargazers_count": 5,
    "release_latest": {
      "tag_name": "v3.3.6",
      "published_at": "2021-10-07T16:37:26Z"
    }
  },
  {
    "pushed_at": "2021-10-18T14:30:21Z",
    "name": "js",
    "description": "javascript utils",
    "open_issues": 1,
    "stargazers_count": 2,
    "release_latest": {
      "tag_name": "v1.8.2",
      "published_at": "2021-10-18T14:30:21Z"
    }
  },
  {
    "pushed_at": "2021-10-18T14:08:44Z",
    "name": "href.attr",
    "description": "ui-href-attribute, every element can be a link",
    "open_issues": 0,
    "stargazers_count": 1,
    "release_latest": {
      "tag_name": "v1.8.3",
      "published_at": "2021-10-18T14:08:44Z"
    }
  },
  {
    "pushed_at": "2021-10-18T14:44:33Z",
    "name": "u1",
    "description": "The Home of the U1 project",
    "open_issues": 0,
    "stargazers_count": 1,
    "release_latest": {
      "tag_name": "v1.9.0",
      "published_at": "2021-10-18T14:08:08Z"
    }
  },
  {
    "pushed_at": "2021-10-18T14:07:10Z",
    "name": "norm.css",
    "description": "Up to date css normalize",
    "open_issues": 0,
    "stargazers_count": 0,
    "release_latest": {
      "tag_name": "v1.8.2",
      "published_at": "2021-10-18T14:07:10Z"
    }
  },
  {
    "pushed_at": "2021-10-07T08:52:37Z",
    "name": "base.css",
    "description": "Usefull css defaults",
    "open_issues": 1,
    "stargazers_count": 0,
    "release_latest": {
      "tag_name": "1.8.5",
      "published_at": "2021-10-07T08:52:37Z"
    }
  },
  {
    "pushed_at": "2021-10-18T14:06:31Z",
    "name": "classless.css",
    "description": null,
    "open_issues": 2,
    "stargazers_count": 2,
    "release_latest": {
      "tag_name": "v1.8.5",
      "published_at": "2021-10-18T14:06:32Z"
    }
  },
  {
    "pushed_at": "2021-10-18T14:05:43Z",
    "name": "classes.css",
    "description": null,
    "open_issues": 0,
    "stargazers_count": 0,
    "release_latest": {
      "tag_name": "v1.8.2",
      "published_at": "2021-10-18T14:05:43Z"
    }
  },
  {
    "pushed_at": "2021-10-07T16:21:56Z",
    "name": "parallax.attr",
    "description": "Make every element scrolling at different speed",
    "open_issues": 0,
    "stargazers_count": 3,
    "release_latest": {
      "tag_name": "v1.8.4",
      "published_at": "2021-10-07T16:21:56Z"
    }
  },
  {
    "pushed_at": "2021-07-12T07:54:02Z",
    "name": "ico.el",
    "description": "universal icon-element",
    "open_issues": 0,
    "stargazers_count": 0,
    "release_latest": {
      "tag_name": "v1.8.1",
      "published_at": "2021-07-12T07:54:02Z"
    }
  },
  {
    "pushed_at": "2021-10-18T14:05:07Z",
    "name": "flex-gap.class",
    "description": "flexbox gappers helper because of safari",
    "open_issues": 0,
    "stargazers_count": 0,
    "release_latest": {
      "tag_name": "v1.8.1",
      "published_at": "2021-10-18T14:05:07Z"
    }
  },
  {
    "pushed_at": "2021-08-23T18:50:13Z",
    "name": "table.class",
    "description": "u1-table class | better tables",
    "open_issues": 0,
    "stargazers_count": 0,
    "release_latest": {
      "tag_name": "v1.8.3",
      "published_at": "2021-08-23T18:50:13Z"
    }
  },
  {
    "pushed_at": "2021-10-18T14:04:37Z",
    "name": "auto-grid.class",
    "description": "most used case for grid-elements",
    "open_issues": 0,
    "stargazers_count": 0,
    "release_latest": {
      "tag_name": "v1.8.2",
      "published_at": "2021-10-18T14:04:37Z"
    }
  },
  {
    "pushed_at": "2021-07-03T00:06:52Z",
    "name": "reset.class",
    "description": "A class to reset Styles",
    "open_issues": 0,
    "stargazers_count": 0,
    "release_latest": {
      "tag_name": "v1.8.0",
      "published_at": "2021-07-03T00:06:52Z"
    }
  },
  {
    "pushed_at": "2021-10-18T14:04:04Z",
    "name": "unstyle.class",
    "description": "css class to unstyle elements eg. buttons",
    "open_issues": 1,
    "stargazers_count": 1,
    "release_latest": {
      "tag_name": "v1.8.1",
      "published_at": "2021-10-18T14:04:05Z"
    }
  },
  {
    "pushed_at": "2021-10-18T14:02:36Z",
    "name": "badge.class",
    "description": "u1-badge class for rendering badges",
    "open_issues": 0,
    "stargazers_count": 1,
    "release_latest": {
      "tag_name": "v1.8.1",
      "published_at": "2021-10-18T14:02:36Z"
    }
  },
  {
    "pushed_at": "2021-07-28T11:47:42Z",
    "name": "tabs.el",
    "description": "u1-tabs element for rendering tabs",
    "open_issues": 0,
    "stargazers_count": 0,
    "release_latest": {
      "tag_name": "v1.8.2",
      "published_at": "2021-07-28T11:47:42Z"
    }
  },
  {
    "pushed_at": "2021-07-28T11:46:29Z",
    "name": "width.class",
    "description": null,
    "open_issues": 0,
    "stargazers_count": 0,
    "release_latest": {
      "tag_name": "v1.8.1",
      "published_at": "2021-07-28T11:46:29Z"
    }
  },
  {
    "pushed_at": "2021-11-03T01:41:11Z",
    "name": "carousel.el",
    "description": null,
    "open_issues": 0,
    "stargazers_count": 0,
    "release_latest": {
      "tag_name": "v1.8.4",
      "published_at": "2021-11-03T01:41:11Z"
    }
  },
  {
    "pushed_at": "2021-07-03T00:06:03Z",
    "name": "input.class",
    "description": null,
    "open_issues": 0,
    "stargazers_count": 0,
    "release_latest": {
      "tag_name": "v1.8.0",
      "published_at": "2021-07-03T00:06:03Z"
    }
  },
  {
    "pushed_at": "2021-07-28T11:46:40Z",
    "name": "time.el",
    "description": "The better time-element, e.g. live changing relative dates",
    "open_issues": 0,
    "stargazers_count": 0,
    "release_latest": {
      "tag_name": "v1.8.2",
      "published_at": "2021-07-28T11:46:40Z"
    }
  },
  {
    "pushed_at": "2021-07-28T11:46:59Z",
    "name": "counter.el",
    "description": "counting numbers",
    "open_issues": 0,
    "stargazers_count": 0,
    "release_latest": {
      "tag_name": "v1.8.0",
      "published_at": "2021-07-28T11:46:59Z"
    }
  },
  {
    "pushed_at": "2021-07-28T11:47:11Z",
    "name": "textfit.el",
    "description": "Exactly fit text",
    "open_issues": 0,
    "stargazers_count": 0,
    "release_latest": {
      "tag_name": "v1.8.0",
      "published_at": "2021-07-28T11:47:12Z"
    }
  },
  {
    "pushed_at": "2021-10-18T14:01:55Z",
    "name": "qrcode.el",
    "description": "qr code element",
    "open_issues": 0,
    "stargazers_count": 0,
    "release_latest": {
      "tag_name": "v1.1.0",
      "published_at": "2021-10-18T14:01:55Z"
    }
  },
  {
    "pushed_at": "2021-10-18T14:00:40Z",
    "name": "card1.class",
    "description": "card-class",
    "open_issues": 0,
    "stargazers_count": 0,
    "release_latest": {
      "tag_name": "v1.1.0",
      "published_at": "2021-10-18T14:00:40Z"
    }
  },
  {
    "pushed_at": "2021-10-28T02:48:34Z",
    "name": "intersect.attr",
    "description": null,
    "open_issues": 0,
    "stargazers_count": 0,
    "release_latest": {
      "tag_name": "v1.8.0",
      "published_at": "2021-10-28T01:33:28Z"
    }
  },
  {
    "pushed_at": "2021-11-03T01:40:34Z",
    "name": "carousel-nav.el",
    "description": null,
    "open_issues": 0,
    "stargazers_count": 0,
    "release_latest": {
      "tag_name": "v1.8.0",
      "published_at": "2021-11-03T01:40:35Z"
    }
  }
]